cirrondly_cli/__init__.py
cirrondly_cli/cli.py
cirrondly_cli/conf.py
cirrondly_cli/events/__init__.py
cirrondly_cli/events/sender.py
cirrondly_cli/exceptions/__init__.py
cirrondly_cli/exceptions/handler.py
cirrondly_cli/frameworks/__init__.py
cirrondly_cli/frameworks/auto_apply_middleware.py
cirrondly_cli/frameworks/django_middleware.py
cirrondly_cli/frameworks/fastapi_middleware.py
cirrondly_cli/frameworks/flask_middleware.py
cirrondly_cli/http/__init__.py
cirrondly_cli/http/request.py
cirrondly_cli/logging/__init__.py
cirrondly_cli/logging/handlers.py
cirrondly_cli/logging/log-handler.py
cirrondly_cli/monitoring/__init__.py
cirrondly_cli/monitoring/event_data.py
cirrondly_cli/monitoring/lifecycle.py
cirrondly_cli/monitoring/metrics.py
cirrondly_cli/queue/__init__.py
cirrondly_cli/queue/manager.py
cirrondly_cli/tools/__init__.py
cirrondly_cli/tools/providers.py
cirrondly_cli/tools/detection/__init__.py
cirrondly_cli/tools/detection/container.py
cirrondly_cli/tools/detection/environment.py
cirrondly_cli/tools/detection/providers.py
cirrondly_cli/tools/detection/region.py
pyarmor_runtime_000000/__init__.py
cirrondly_cli-0.1.112.dist-info/METADATA
cirrondly_cli-0.1.112.dist-info/WHEEL
cirrondly_cli-0.1.112.dist-info/entry_points.txt
cirrondly_cli-0.1.112.dist-info/top_level.txt
cirrondly_cli-0.1.112.dist-info/RECORD
