Metadata-Version: 2.4
Name: cirrondly-cli
Version: 0.1.112
Summary: Cirrondly agent installer and guard CLI
Author-email: Jose MARIN <contact@cirrondly.com>
License-Expression: MIT
Project-URL: homepage, https://cirrondly.com/
Requires-Python: >=3.8
Requires-Dist: requests
Requires-Dist: psutil
Requires-Dist: python-dotenv
